tronalddump/__init__.py
tronalddump/td.py
tronalddump-0.4.dist-info/METADATA
tronalddump-0.4.dist-info/RECORD
tronalddump-0.4.dist-info/WHEEL
tronalddump-0.4.dist-info/top_level.txt
